{
    "variable": [
        {
            "id": "baseUrl",
            "key": "baseUrl",
            "type": "string",
            "name": "string",
            "value": "http:\/\/localhost"
        }
    ],
    "info": {
        "name": "Hospital Management System API Docs",
        "_postman_id": "88849122-f3eb-4844-9462-ec4089eac817",
        "description": "Hospital Management System API Docs",
        "schema": "https:\/\/schema.getpostman.com\/json\/collection\/v2.1.0\/collection.json"
    },
    "item": [
        {
            "name": "Endpoints",
            "description": "",
            "item": [
                {
                    "name": "POST api\/register",
                    "request": {
                        "url": {
                            "host": "{{baseUrl}}",
                            "path": "api\/register",
                            "query": [],
                            "raw": "{{baseUrl}}\/api\/register"
                        },
                        "method": "POST",
                        "header": [
                            {
                                "key": "Content-Type",
                                "value": "application\/json"
                            },
                            {
                                "key": "Accept",
                                "value": "application\/json"
                            }
                        ],
                        "body": null,
                        "description": "",
                        "auth": {
                            "type": "noauth"
                        }
                    },
                    "response": []
                },
                {
                    "name": "POST api\/login-user",
                    "request": {
                        "url": {
                            "host": "{{baseUrl}}",
                            "path": "api\/login-user",
                            "query": [],
                            "raw": "{{baseUrl}}\/api\/login-user"
                        },
                        "method": "POST",
                        "header": [
                            {
                                "key": "Content-Type",
                                "value": "application\/json"
                            },
                            {
                                "key": "Accept",
                                "value": "application\/json"
                            }
                        ],
                        "body": null,
                        "description": "",
                        "auth": {
                            "type": "noauth"
                        }
                    },
                    "response": []
                },
                {
                    "name": "GET api\/user",
                    "request": {
                        "url": {
                            "host": "{{baseUrl}}",
                            "path": "api\/user",
                            "query": [],
                            "raw": "{{baseUrl}}\/api\/user"
                        },
                        "method": "GET",
                        "header": [
                            {
                                "key": "Content-Type",
                                "value": "application\/json"
                            },
                            {
                                "key": "Accept",
                                "value": "application\/json"
                            }
                        ],
                        "body": null,
                        "description": "",
                        "auth": {
                            "type": "noauth"
                        }
                    },
                    "response": [
                        {
                            "header": [
                                {
                                    "key": "cache-control",
                                    "value": "no-cache, private"
                                },
                                {
                                    "key": "content-type",
                                    "value": "application\/json"
                                },
                                {
                                    "key": "access-control-allow-origin",
                                    "value": "*"
                                }
                            ],
                            "code": 401,
                            "body": "{\"message\":\"Unauthenticated.\"}",
                            "name": ""
                        }
                    ]
                },
                {
                    "name": "PATIENTS :: List",
                    "request": {
                        "url": {
                            "host": "{{baseUrl}}",
                            "path": "api\/patients",
                            "query": [],
                            "raw": "{{baseUrl}}\/api\/patients"
                        },
                        "method": "POST",
                        "header": [
                            {
                                "key": "Content-Type",
                                "value": "application\/json"
                            },
                            {
                                "key": "Accept",
                                "value": "application\/json"
                            }
                        ],
                        "body": null,
                        "description": "",
                        "auth": {
                            "type": "noauth"
                        }
                    },
                    "response": []
                },
                {
                    "name": "PATIENTS :: Store",
                    "request": {
                        "url": {
                            "host": "{{baseUrl}}",
                            "path": "api\/patients\/add",
                            "query": [],
                            "raw": "{{baseUrl}}\/api\/patients\/add"
                        },
                        "method": "POST",
                        "header": [
                            {
                                "key": "Content-Type",
                                "value": "application\/json"
                            },
                            {
                                "key": "Accept",
                                "value": "application\/json"
                            }
                        ],
                        "body": {
                            "mode": "raw",
                            "raw": "{\"identifier_number\":\"eos\",\"blood_group\":\"y\",\"email\":\"robin69@example.org\",\"city_id\":10,\"first_name\":\"axxzginbnxzxxjj\",\"last_name\":\"zpfxwlbyriindflbwcn\",\"date_of_birth\":\"2024-06-24T13:53:23\",\"gender\":\"zbn\",\"phones\":\"gsodt\"}"
                        },
                        "description": "",
                        "auth": {
                            "type": "noauth"
                        }
                    },
                    "response": []
                },
                {
                    "name": "Display the specified resource.",
                    "request": {
                        "url": {
                            "host": "{{baseUrl}}",
                            "path": "api\/patients\/show",
                            "query": [],
                            "raw": "{{baseUrl}}\/api\/patients\/show"
                        },
                        "method": "POST",
                        "header": [
                            {
                                "key": "Content-Type",
                                "value": "application\/json"
                            },
                            {
                                "key": "Accept",
                                "value": "application\/json"
                            }
                        ],
                        "body": null,
                        "description": "",
                        "auth": {
                            "type": "noauth"
                        }
                    },
                    "response": []
                },
                {
                    "name": "POST api\/patients\/bulk-upload-patients",
                    "request": {
                        "url": {
                            "host": "{{baseUrl}}",
                            "path": "api\/patients\/bulk-upload-patients",
                            "query": [],
                            "raw": "{{baseUrl}}\/api\/patients\/bulk-upload-patients"
                        },
                        "method": "POST",
                        "header": [
                            {
                                "key": "Content-Type",
                                "value": "application\/json"
                            },
                            {
                                "key": "Accept",
                                "value": "application\/json"
                            }
                        ],
                        "body": null,
                        "description": "",
                        "auth": {
                            "type": "noauth"
                        }
                    },
                    "response": []
                },
                {
                    "name": "Update the specified resource in storage.",
                    "request": {
                        "url": {
                            "host": "{{baseUrl}}",
                            "path": "api\/patients\/update",
                            "query": [],
                            "raw": "{{baseUrl}}\/api\/patients\/update"
                        },
                        "method": "POST",
                        "header": [
                            {
                                "key": "Content-Type",
                                "value": "application\/json"
                            },
                            {
                                "key": "Accept",
                                "value": "application\/json"
                            }
                        ],
                        "body": {
                            "mode": "raw",
                            "raw": "{\"identifier_number\":\"officia\",\"blood_group\":\"mfafqxdivbvxnvned\",\"city_id\":12,\"first_name\":\"hny\",\"last_name\":\"kxsciaoeig\",\"date_of_birth\":\"2024-06-24T13:53:23\",\"gender\":\"xfuiyuota\",\"phones\":\"b\"}"
                        },
                        "description": "",
                        "auth": {
                            "type": "noauth"
                        }
                    },
                    "response": []
                },
                {
                    "name": "Remove the specified resource from storage.",
                    "request": {
                        "url": {
                            "host": "{{baseUrl}}",
                            "path": "api\/patients\/delete",
                            "query": [],
                            "raw": "{{baseUrl}}\/api\/patients\/delete"
                        },
                        "method": "POST",
                        "header": [
                            {
                                "key": "Content-Type",
                                "value": "application\/json"
                            },
                            {
                                "key": "Accept",
                                "value": "application\/json"
                            }
                        ],
                        "body": {
                            "mode": "raw",
                            "raw": "{\"patient_id\":\"tempora\"}"
                        },
                        "description": "",
                        "auth": {
                            "type": "noauth"
                        }
                    },
                    "response": []
                },
                {
                    "name": "PATIENT VISITS :: List",
                    "request": {
                        "url": {
                            "host": "{{baseUrl}}",
                            "path": "api\/patient-visits",
                            "query": [],
                            "raw": "{{baseUrl}}\/api\/patient-visits"
                        },
                        "method": "POST",
                        "header": [
                            {
                                "key": "Content-Type",
                                "value": "application\/json"
                            },
                            {
                                "key": "Accept",
                                "value": "application\/json"
                            }
                        ],
                        "body": null,
                        "description": "",
                        "auth": {
                            "type": "noauth"
                        }
                    },
                    "response": []
                },
                {
                    "name": "PATIENT VISITS :: Store",
                    "request": {
                        "url": {
                            "host": "{{baseUrl}}",
                            "path": "api\/patient-visits\/add",
                            "query": [],
                            "raw": "{{baseUrl}}\/api\/patient-visits\/add"
                        },
                        "method": "POST",
                        "header": [
                            {
                                "key": "Content-Type",
                                "value": "application\/json"
                            },
                            {
                                "key": "Accept",
                                "value": "application\/json"
                            }
                        ],
                        "body": null,
                        "description": "",
                        "auth": {
                            "type": "noauth"
                        }
                    },
                    "response": []
                },
                {
                    "name": "Display the specified resource.",
                    "request": {
                        "url": {
                            "host": "{{baseUrl}}",
                            "path": "api\/patient-visits\/show",
                            "query": [],
                            "raw": "{{baseUrl}}\/api\/patient-visits\/show"
                        },
                        "method": "POST",
                        "header": [
                            {
                                "key": "Content-Type",
                                "value": "application\/json"
                            },
                            {
                                "key": "Accept",
                                "value": "application\/json"
                            }
                        ],
                        "body": null,
                        "description": "",
                        "auth": {
                            "type": "noauth"
                        }
                    },
                    "response": []
                },
                {
                    "name": "POST api\/logout-user",
                    "request": {
                        "url": {
                            "host": "{{baseUrl}}",
                            "path": "api\/logout-user",
                            "query": [],
                            "raw": "{{baseUrl}}\/api\/logout-user"
                        },
                        "method": "POST",
                        "header": [
                            {
                                "key": "Content-Type",
                                "value": "application\/json"
                            },
                            {
                                "key": "Accept",
                                "value": "application\/json"
                            }
                        ],
                        "body": null,
                        "description": "",
                        "auth": {
                            "type": "noauth"
                        }
                    },
                    "response": []
                },
                {
                    "name": "CITIES :: List",
                    "request": {
                        "url": {
                            "host": "{{baseUrl}}",
                            "path": "api\/cities",
                            "query": [],
                            "raw": "{{baseUrl}}\/api\/cities"
                        },
                        "method": "POST",
                        "header": [
                            {
                                "key": "Content-Type",
                                "value": "application\/json"
                            },
                            {
                                "key": "Accept",
                                "value": "application\/json"
                            }
                        ],
                        "body": null,
                        "description": "",
                        "auth": {
                            "type": "noauth"
                        }
                    },
                    "response": []
                },
                {
                    "name": "DEPARTMENTS :: List",
                    "request": {
                        "url": {
                            "host": "{{baseUrl}}",
                            "path": "api\/departments",
                            "query": [],
                            "raw": "{{baseUrl}}\/api\/departments"
                        },
                        "method": "POST",
                        "header": [
                            {
                                "key": "Content-Type",
                                "value": "application\/json"
                            },
                            {
                                "key": "Accept",
                                "value": "application\/json"
                            }
                        ],
                        "body": null,
                        "description": "",
                        "auth": {
                            "type": "noauth"
                        }
                    },
                    "response": []
                },
                {
                    "name": "Display a listing of the resource.",
                    "request": {
                        "url": {
                            "host": "{{baseUrl}}",
                            "path": "api\/consultation",
                            "query": [],
                            "raw": "{{baseUrl}}\/api\/consultation"
                        },
                        "method": "POST",
                        "header": [
                            {
                                "key": "Content-Type",
                                "value": "application\/json"
                            },
                            {
                                "key": "Accept",
                                "value": "application\/json"
                            }
                        ],
                        "body": null,
                        "description": "",
                        "auth": {
                            "type": "noauth"
                        }
                    },
                    "response": []
                },
                {
                    "name": "CONSULTATION :: Store",
                    "request": {
                        "url": {
                            "host": "{{baseUrl}}",
                            "path": "api\/consultation\/add",
                            "query": [],
                            "raw": "{{baseUrl}}\/api\/consultation\/add"
                        },
                        "method": "POST",
                        "header": [
                            {
                                "key": "Content-Type",
                                "value": "application\/json"
                            },
                            {
                                "key": "Accept",
                                "value": "application\/json"
                            }
                        ],
                        "body": null,
                        "description": "",
                        "auth": {
                            "type": "noauth"
                        }
                    },
                    "response": []
                },
                {
                    "name": "Display the specified resource.",
                    "request": {
                        "url": {
                            "host": "{{baseUrl}}",
                            "path": "api\/consultation\/show",
                            "query": [],
                            "raw": "{{baseUrl}}\/api\/consultation\/show"
                        },
                        "method": "POST",
                        "header": [
                            {
                                "key": "Content-Type",
                                "value": "application\/json"
                            },
                            {
                                "key": "Accept",
                                "value": "application\/json"
                            }
                        ],
                        "body": null,
                        "description": "",
                        "auth": {
                            "type": "noauth"
                        }
                    },
                    "response": []
                },
                {
                    "name": "PHONES :: Store",
                    "request": {
                        "url": {
                            "host": "{{baseUrl}}",
                            "path": "api\/people\/people\/:person_id\/phones",
                            "query": [],
                            "raw": "{{baseUrl}}\/api\/people\/people\/:person_id\/phones",
                            "variable": [
                                {
                                    "id": "person_id",
                                    "key": "person_id",
                                    "value": "consequatur",
                                    "description": "The ID of the person."
                                }
                            ]
                        },
                        "method": "POST",
                        "header": [
                            {
                                "key": "Content-Type",
                                "value": "application\/json"
                            },
                            {
                                "key": "Accept",
                                "value": "application\/json"
                            }
                        ],
                        "body": {
                            "mode": "raw",
                            "raw": "{\"phone_number\":\"dnti\"}"
                        },
                        "description": "",
                        "auth": {
                            "type": "noauth"
                        }
                    },
                    "response": []
                }
            ]
        }
    ],
    "auth": {
        "type": "noauth"
    }
}